optumi_api/CloudFile.py
optumi_api/CloudFileVersion.py
optumi_api/CloudStorage.py
optumi_api/Colab.py
optumi_api/Container.py
optumi_api/ContainerRegistry.py
optumi_api/EnvironmentVariables.py
optumi_api/Executable.py
optumi_api/LocalFile.py
optumi_api/LocalStorage.py
optumi_api/Log.py
optumi_api/LoginServer.py
optumi_api/Machine.py
optumi_api/Machines.py
optumi_api/Notebook.py
optumi_api/Notifications.py
optumi_api/Packages.py
optumi_api/Profile.py
optumi_api/Program.py
optumi_api/Provider.py
optumi_api/Providers.py
optumi_api/Resource.py
optumi_api/Script.py
optumi_api/Server.py
optumi_api/Summary.py
optumi_api/Workload.py
optumi_api/Workloads.py
optumi_api/__init__.py
optumi_api/_version.py
optumi_api/api.py
optumi_api/cli.py
optumi_api/utils.py
optumi_api-3.17.0.dist-info/LICENSE
optumi_api-3.17.0.dist-info/METADATA
optumi_api-3.17.0.dist-info/WHEEL
optumi_api-3.17.0.dist-info/entry_points.txt
optumi_api-3.17.0.dist-info/top_level.txt
optumi_api-3.17.0.dist-info/RECORD
