Metadata-Version: 2.1
Name: optumi-api
Version: 3.17.0
Summary: Optumi api library
Home-page: https://optumi.com
Author: Optumi Inc Authors
Author-email: cs@optumi.com
Keywords: Optumi
Platform: Linux
Platform: Mac OS X
Platform: Windows
Classifier: License :: Other/Proprietary License
Classifier: Development Status :: 4 - Beta
Classifier: Programming Language :: Python
Classifier: Programming Language :: Python :: 3
Classifier: Programming Language :: Python :: 3.7
Classifier: Programming Language :: Python :: 3.8
Classifier: Programming Language :: Python :: 3.9
Classifier: Operating System :: OS Independent
Classifier: Intended Audience :: Developers
Classifier: Intended Audience :: System Administrators
Classifier: Intended Audience :: Science/Research
Classifier: Topic :: Scientific/Engineering
Classifier: Topic :: Scientific/Engineering :: Artificial Intelligence
Classifier: Topic :: Software Development
Classifier: Topic :: Software Development :: Libraries
Classifier: Topic :: Software Development :: Libraries :: Python Modules
Requires-Python: >=3.7
License-File: LICENSE
Requires-Dist: optumi-core ~=3.17.0
Requires-Dist: phonenumbers
Requires-Dist: pwinput
Requires-Dist: tornado
Requires-Dist: requests
Requires-Dist: python-dateutil
